<?xml version="1.0" encoding="UTF-8" standalone="yes"?>
<w:document xmlns:wpc="http://schemas.microsoft.com/office/word/2010/wordprocessingCanvas" xmlns:mc="http://schemas.openxmlformats.org/markup-compatibility/2006" xmlns:o="urn:schemas-microsoft-com:office:office" xmlns:r="http://schemas.openxmlformats.org/officeDocument/2006/relationships" xmlns:m="http://schemas.openxmlformats.org/officeDocument/2006/math" xmlns:v="urn:schemas-microsoft-com:vml" xmlns:wp14="http://schemas.microsoft.com/office/word/2010/wordprocessingDrawing" xmlns:wp="http://schemas.openxmlformats.org/drawingml/2006/wordprocessingDrawing" xmlns:w10="urn:schemas-microsoft-com:office:word" xmlns:w="http://schemas.openxmlformats.org/wordprocessingml/2006/main" xmlns:w14="http://schemas.microsoft.com/office/word/2010/wordml" xmlns:w15="http://schemas.microsoft.com/office/word/2012/wordml" xmlns:wpg="http://schemas.microsoft.com/office/word/2010/wordprocessingGroup" xmlns:wpi="http://schemas.microsoft.com/office/word/2010/wordprocessingInk" xmlns:wne="http://schemas.microsoft.com/office/word/2006/wordml" xmlns:wps="http://schemas.microsoft.com/office/word/2010/wordprocessingShape" mc:Ignorable="w14 w15 wp14"><w:body><w:p w:rsidR="005A007A" w:rsidRDefault="00263AF6" w:rsidP="003C2810"><w:pPr><w:rPr><w:color w:val="666666"/><w:sz w:val="23"/><w:szCs w:val="23"/><w:shd w:val="clear" w:color="auto" w:fill="FFFFFF"/></w:rPr></w:pPr><w:r><w:rPr><w:color w:val="666666"/><w:sz w:val="23"/><w:szCs w:val="23"/><w:shd w:val="clear" w:color="auto" w:fill="FFFFFF"/></w:rPr><w:t xml:space="preserve">Baru </w:t></w:r><w:bookmarkStart w:id="0" w:name="_GoBack"/><w:bookmarkEnd w:id="0"/><w:r w:rsidR="005A007A"><w:rPr><w:color w:val="666666"/><w:sz w:val="23"/><w:szCs w:val="23"/><w:shd w:val="clear" w:color="auto" w:fill="FFFFFF"/></w:rPr><w:t>Pertanyaan</w:t></w:r><w:r w:rsidR="00910C69"><w:rPr><w:color w:val="666666"/><w:sz w:val="23"/><w:szCs w:val="23"/><w:shd w:val="clear" w:color="auto" w:fill="FFFFFF"/></w:rPr><w:t xml:space="preserve"> </w:t></w:r><m:oMath><m:sSup><m:sSupPr><m:ctrlPr><w:rPr><w:rFonts w:ascii="Cambria Math" w:hAnsi="Cambria Math"/><w:color w:val="666666"/><w:sz w:val="23"/><w:szCs w:val="23"/><w:shd w:val="clear" w:color="auto" w:fill="FFFFFF"/></w:rPr></m:ctrlPr></m:sSupPr><m:e><m:d><m:dPr><m:ctrlPr><w:rPr><w:rFonts w:ascii="Cambria Math" w:hAnsi="Cambria Math"/><w:color w:val="666666"/><w:sz w:val="23"/><w:szCs w:val="23"/><w:shd w:val="clear" w:color="auto" w:fill="FFFFFF"/></w:rPr></m:ctrlPr></m:dPr><m:e><m:r><w:rPr><w:rFonts w:ascii="Cambria Math" w:hAnsi="Cambria Math"/><w:color w:val="666666"/><w:sz w:val="23"/><w:szCs w:val="23"/><w:shd w:val="clear" w:color="auto" w:fill="FFFFFF"/></w:rPr><m:t>x+a</m:t></m:r></m:e></m:d></m:e><m:sup><m:r><w:rPr><w:rFonts w:ascii="Cambria Math" w:hAnsi="Cambria Math"/><w:color w:val="666666"/><w:sz w:val="23"/><w:szCs w:val="23"/><w:shd w:val="clear" w:color="auto" w:fill="FFFFFF"/></w:rPr><m:t>n</m:t></m:r></m:sup></m:sSup><m:r><w:rPr><w:rFonts w:ascii="Cambria Math" w:eastAsia="Cambria Math" w:hAnsi="Cambria Math" w:cs="Cambria Math"/><w:color w:val="666666"/><w:sz w:val="23"/><w:szCs w:val="23"/><w:shd w:val="clear" w:color="auto" w:fill="FFFFFF"/></w:rPr><m:t>=</m:t></m:r><m:nary><m:naryPr><m:chr m:val="∑"/><m:grow m:val="1"/><m:ctrlPr><w:rPr><w:rFonts w:ascii="Cambria Math" w:hAnsi="Cambria Math"/><w:color w:val="666666"/><w:sz w:val="23"/><w:szCs w:val="23"/><w:shd w:val="clear" w:color="auto" w:fill="FFFFFF"/></w:rPr></m:ctrlPr></m:naryPr><m:sub><m:r><w:rPr><w:rFonts w:ascii="Cambria Math" w:eastAsia="Cambria Math" w:hAnsi="Cambria Math" w:cs="Cambria Math"/><w:color w:val="666666"/><w:sz w:val="23"/><w:szCs w:val="23"/><w:shd w:val="clear" w:color="auto" w:fill="FFFFFF"/></w:rPr><m:t>k=0</m:t></m:r></m:sub><m:sup><m:r><w:rPr><w:rFonts w:ascii="Cambria Math" w:eastAsia="Cambria Math" w:hAnsi="Cambria Math" w:cs="Cambria Math"/><w:color w:val="666666"/><w:sz w:val="23"/><w:szCs w:val="23"/><w:shd w:val="clear" w:color="auto" w:fill="FFFFFF"/></w:rPr><m:t>n</m:t></m:r></m:sup><m:e><m:d><m:dPr><m:ctrlPr><w:rPr><w:rFonts w:ascii="Cambria Math" w:hAnsi="Cambria Math"/><w:color w:val="666666"/><w:sz w:val="23"/><w:szCs w:val="23"/><w:shd w:val="clear" w:color="auto" w:fill="FFFFFF"/></w:rPr></m:ctrlPr></m:dPr><m:e><m:f><m:fPr><m:type m:val="noBar"/><m:ctrlPr><w:rPr><w:rFonts w:ascii="Cambria Math" w:hAnsi="Cambria Math"/><w:color w:val="666666"/><w:sz w:val="23"/><w:szCs w:val="23"/><w:shd w:val="clear" w:color="auto" w:fill="FFFFFF"/></w:rPr></m:ctrlPr></m:fPr><m:num><m:r><w:rPr><w:rFonts w:ascii="Cambria Math" w:eastAsia="Cambria Math" w:hAnsi="Cambria Math" w:cs="Cambria Math"/><w:color w:val="666666"/><w:sz w:val="23"/><w:szCs w:val="23"/><w:shd w:val="clear" w:color="auto" w:fill="FFFFFF"/></w:rPr><m:t>n</m:t></m:r></m:num><m:den><m:r><w:rPr><w:rFonts w:ascii="Cambria Math" w:eastAsia="Cambria Math" w:hAnsi="Cambria Math" w:cs="Cambria Math"/><w:color w:val="666666"/><w:sz w:val="23"/><w:szCs w:val="23"/><w:shd w:val="clear" w:color="auto" w:fill="FFFFFF"/></w:rPr><m:t>k</m:t></m:r></m:den></m:f></m:e></m:d><m:sSup><m:sSupPr><m:ctrlPr><w:rPr><w:rFonts w:ascii="Cambria Math" w:hAnsi="Cambria Math"/><w:color w:val="666666"/><w:sz w:val="23"/><w:szCs w:val="23"/><w:shd w:val="clear" w:color="auto" w:fill="FFFFFF"/></w:rPr></m:ctrlPr></m:sSupPr><m:e><m:r><w:rPr><w:rFonts w:ascii="Cambria Math" w:eastAsia="Cambria Math" w:hAnsi="Cambria Math" w:cs="Cambria Math"/><w:color w:val="666666"/><w:sz w:val="23"/><w:szCs w:val="23"/><w:shd w:val="clear" w:color="auto" w:fill="FFFFFF"/></w:rPr><m:t>x</m:t></m:r></m:e><m:sup><m:r><w:rPr><w:rFonts w:ascii="Cambria Math" w:eastAsia="Cambria Math" w:hAnsi="Cambria Math" w:cs="Cambria Math"/><w:color w:val="666666"/><w:sz w:val="23"/><w:szCs w:val="23"/><w:shd w:val="clear" w:color="auto" w:fill="FFFFFF"/></w:rPr><m:t>k</m:t></m:r></m:sup></m:sSup><m:sSup><m:sSupPr><m:ctrlPr><w:rPr><w:rFonts w:ascii="Cambria Math" w:hAnsi="Cambria Math"/><w:color w:val="666666"/><w:sz w:val="23"/><w:szCs w:val="23"/><w:shd w:val="clear" w:color="auto" w:fill="FFFFFF"/></w:rPr></m:ctrlPr></m:sSupPr><m:e><m:r><w:rPr><w:rFonts w:ascii="Cambria Math" w:eastAsia="Cambria Math" w:hAnsi="Cambria Math" w:cs="Cambria Math"/><w:color w:val="666666"/><w:sz w:val="23"/><w:szCs w:val="23"/><w:shd w:val="clear" w:color="auto" w:fill="FFFFFF"/></w:rPr><m:t>a</m:t></m:r></m:e><m:sup><m:r><w:rPr><w:rFonts w:ascii="Cambria Math" w:eastAsia="Cambria Math" w:hAnsi="Cambria Math" w:cs="Cambria Math"/><w:color w:val="666666"/><w:sz w:val="23"/><w:szCs w:val="23"/><w:shd w:val="clear" w:color="auto" w:fill="FFFFFF"/></w:rPr><m:t>n-k</m:t></m:r></m:sup></m:sSup></m:e></m:nary></m:oMath></w:p><w:p w:rsidR="003C2810" w:rsidRDefault="003C2810" w:rsidP="003C2810"><w:pPr><w:rPr><w:color w:val="666666"/><w:sz w:val="23"/><w:szCs w:val="23"/><w:shd w:val="clear" w:color="auto" w:fill="FFFFFF"/></w:rPr></w:pPr><w:r w:rsidRPr="0006679B"><w:rPr><w:color w:val="666666"/><w:sz w:val="23"/><w:szCs w:val="23"/><w:shd w:val="clear" w:color="auto" w:fill="FFFFFF"/></w:rPr><w:t xml:space="preserve">Untuk sekedar sebagai class bantuan dalam hal manipulasi file teks, </w:t></w:r><w:r w:rsidR="00DB2644"><w:rPr><w:color w:val="666666"/><w:sz w:val="23"/><w:szCs w:val="23"/><w:shd w:val="clear" w:color="auto" w:fill="FFFFFF"/></w:rPr><w:t>\n</w:t></w:r><w:r w:rsidRPr="0006679B"><w:rPr><w:color w:val="666666"/><w:sz w:val="23"/><w:szCs w:val="23"/><w:shd w:val="clear" w:color="auto" w:fill="FFFFFF"/></w:rPr><w:t>maka yang perlu dibuat adalah method untuk menentukan lokasi file, membaca file, dan terakhir adalah menulis data ke dalam file. Semua method tersebut harus bisa diakses dari seluruh bagian program dengan dependensi seminim mungkin. Karena itu, sebaiknya method tersebut dibuat sebagai static method, dalam sebuah class tersendiri. Buatlah class seperti di bawah ini.</w:t></w:r></w:p><w:p w:rsidR="005A007A" w:rsidRDefault="005A007A" w:rsidP="003C2810"><w:pPr><w:rPr><w:color w:val="666666"/><w:sz w:val="23"/><w:szCs w:val="23"/><w:shd w:val="clear" w:color="auto" w:fill="FFFFFF"/></w:rPr></w:pPr><w:r><w:rPr><w:color w:val="666666"/><w:sz w:val="23"/><w:szCs w:val="23"/><w:shd w:val="clear" w:color="auto" w:fill="FFFFFF"/></w:rPr><w:t>Jawab1 A</w:t></w:r></w:p><w:p w:rsidR="003C2810" w:rsidRPr="0069703D" w:rsidRDefault="003C2810" w:rsidP="003C2810"><w:r><w:rPr><w:color w:val="666666"/><w:sz w:val="23"/><w:szCs w:val="23"/><w:shd w:val="clear" w:color="auto" w:fill="FFFFFF"/></w:rPr><w:t xml:space="preserve">Jawab2 </w:t></w:r><w:r w:rsidR="005A007A"><w:rPr><w:color w:val="666666"/><w:sz w:val="23"/><w:szCs w:val="23"/><w:shd w:val="clear" w:color="auto" w:fill="FFFFFF"/></w:rPr><w:t>B</w:t></w:r></w:p><w:p w:rsidR="005A007A" w:rsidRDefault="005A007A" w:rsidP="005A007A"><w:pPr><w:rPr><w:color w:val="666666"/><w:sz w:val="23"/><w:szCs w:val="23"/><w:shd w:val="clear" w:color="auto" w:fill="FFFFFF"/></w:rPr></w:pPr><w:r><w:rPr><w:color w:val="666666"/><w:sz w:val="23"/><w:szCs w:val="23"/><w:shd w:val="clear" w:color="auto" w:fill="FFFFFF"/></w:rPr><w:t>Jawab3</w:t></w:r><w:r w:rsidR="00396DAC"><w:rPr><w:color w:val="666666"/><w:sz w:val="23"/><w:szCs w:val="23"/><w:shd w:val="clear" w:color="auto" w:fill="FFFFFF"/></w:rPr><w:t xml:space="preserve"> </w:t></w:r><w:r><w:rPr><w:color w:val="666666"/><w:sz w:val="23"/><w:szCs w:val="23"/><w:shd w:val="clear" w:color="auto" w:fill="FFFFFF"/></w:rPr><w:t>C</w:t></w:r></w:p><w:p w:rsidR="005A007A" w:rsidRPr="0069703D" w:rsidRDefault="005A007A" w:rsidP="005A007A"><w:r><w:rPr><w:color w:val="666666"/><w:sz w:val="23"/><w:szCs w:val="23"/><w:shd w:val="clear" w:color="auto" w:fill="FFFFFF"/></w:rPr><w:t>Jawab4</w:t></w:r><w:r w:rsidR="00396DAC"><w:rPr><w:color w:val="666666"/><w:sz w:val="23"/><w:szCs w:val="23"/><w:shd w:val="clear" w:color="auto" w:fill="FFFFFF"/></w:rPr><w:t xml:space="preserve"> </w:t></w:r><w:r><w:rPr><w:color w:val="666666"/><w:sz w:val="23"/><w:szCs w:val="23"/><w:shd w:val="clear" w:color="auto" w:fill="FFFFFF"/></w:rPr><w:t>D</w:t></w:r></w:p><w:p w:rsidR="005A007A" w:rsidRDefault="005A007A" w:rsidP="005A007A"><w:pPr><w:rPr><w:color w:val="666666"/><w:sz w:val="23"/><w:szCs w:val="23"/><w:shd w:val="clear" w:color="auto" w:fill="FFFFFF"/></w:rPr></w:pPr><w:r><w:rPr><w:color w:val="666666"/><w:sz w:val="23"/><w:szCs w:val="23"/><w:shd w:val="clear" w:color="auto" w:fill="FFFFFF"/></w:rPr><w:t>Jawab5</w:t></w:r><w:r w:rsidR="00396DAC"><w:rPr><w:color w:val="666666"/><w:sz w:val="23"/><w:szCs w:val="23"/><w:shd w:val="clear" w:color="auto" w:fill="FFFFFF"/></w:rPr><w:t xml:space="preserve"> </w:t></w:r><w:r><w:rPr><w:color w:val="666666"/><w:sz w:val="23"/><w:szCs w:val="23"/><w:shd w:val="clear" w:color="auto" w:fill="FFFFFF"/></w:rPr><w:t>E</w:t></w:r></w:p><w:p w:rsidR="0069703D" w:rsidRDefault="0069703D" w:rsidP="0006679B"/><w:sectPr w:rsidR="0069703D"><w:pgSz w:w="12240" w:h="15840"/><w:pgMar w:top="1440" w:right="1440" w:bottom="1440" w:left="1440" w:header="720" w:footer="720" w:gutter="0"/><w:cols w:space="720"/><w:docGrid w:linePitch="360"/></w:sectPr></w:body></w:document>